vmtp/__init__.py
vmtp/cfg.default.yaml
vmtp/compute.py
vmtp/config.py
vmtp/credentials.py
vmtp/fluentd.py
vmtp/instance.py
vmtp/iperf_tool.py
vmtp/log.py
vmtp/monitor.py
vmtp/network.py
vmtp/nuttcp_tool.py
vmtp/perf_instance.py
vmtp/perf_tool.py
vmtp/pns_mongo.py
vmtp/pnsdb_summary.py
vmtp/sshutils.py
vmtp/vmtp.py
vmtp/vmtp_genchart.py
vmtp/tools/iperf-2.0.9
vmtp/tools/nuttcp-8.1.4
vmtp-2.5.0.dist-info/AUTHORS
vmtp-2.5.0.dist-info/LICENSE
vmtp-2.5.0.dist-info/METADATA
vmtp-2.5.0.dist-info/WHEEL
vmtp-2.5.0.dist-info/entry_points.txt
vmtp-2.5.0.dist-info/pbr.json
vmtp-2.5.0.dist-info/top_level.txt
vmtp-2.5.0.dist-info/RECORD
