Metadata-Version: 2.1
Name: vmtp
Version: 2.5.0
Summary: A data path performance tool for OpenStack clouds.
Home-page: http://vmtp.readthedocs.io/en/latest
Author: OpenStack
Author-email: openstack-discuss@lists.openstack.org
License: UNKNOWN
Platform: UNKNOWN
Classifier: Environment :: OpenStack
Classifier: Intended Audience :: Developers
Classifier: Intended Audience :: Information Technology
Classifier: Intended Audience :: System Administrators
Classifier: License :: OSI Approved :: Apache Software License
Classifier: Operating System :: POSIX :: Linux
Classifier: Operating System :: MacOS
Classifier: Programming Language :: Python
Classifier: Programming Language :: Python :: 2
Classifier: Programming Language :: Python :: 2.7
Requires-Dist: pbr (<2.0,>=1.3)
Requires-Dist: Babel (>=1.3)
Requires-Dist: attrdict (>=2.0.0)
Requires-Dist: lxml (>=3.4.0)
Requires-Dist: paramiko (>=1.14.0)
Requires-Dist: prettytable (>=0.7.2)
Requires-Dist: pymongo (>=2.7.2)
Requires-Dist: pytz (>=2016.4)
Requires-Dist: python-glanceclient (>=0.15.0)
Requires-Dist: python-neutronclient (>=3.0.0)
Requires-Dist: python-novaclient (>=2.18.1)
Requires-Dist: python-openstackclient (>=0.4.1)
Requires-Dist: python-keystoneclient (>=3.10.0)
Requires-Dist: scp (>=0.8.0)
Requires-Dist: tabulate (>=0.7.3)
Requires-Dist: fluent-logger (>=0.5.2)
Requires-Dist: functools32 (>=3.2.3)
